sphinx_immaterial_igwn/__init__.py
sphinx_immaterial_igwn/_version.py
sphinx_immaterial_igwn/defaults.py
sphinx_immaterial_igwn/layout.html
sphinx_immaterial_igwn/theme.conf
sphinx_immaterial_igwn/partials/acknowledgements.html
sphinx_immaterial_igwn/partials/copyright.html
sphinx_immaterial_igwn/partials/source-file.html
sphinx_immaterial_igwn/static/images/favicon.ico
sphinx_immaterial_igwn/static/images/kagra.png
sphinx_immaterial_igwn/static/images/ligo.png
sphinx_immaterial_igwn/static/images/logo.png
sphinx_immaterial_igwn/static/images/lsc.png
sphinx_immaterial_igwn/static/images/virgo.png
sphinx_immaterial_igwn/static/stylesheets/igwn-mkdocs-material.css
sphinx_immaterial_igwn-0.2.0.dist-info/METADATA
sphinx_immaterial_igwn-0.2.0.dist-info/WHEEL
sphinx_immaterial_igwn-0.2.0.dist-info/entry_points.txt
sphinx_immaterial_igwn-0.2.0.dist-info/top_level.txt
sphinx_immaterial_igwn-0.2.0.dist-info/RECORD
